{
  "id": "b0ab5dd2-8c4c-4684-86de-c335cd3311ee",
  "prevId": "00000000-0000-0000-0000-000000000000",
  "version": "5",
  "dialect": "pg",
  "tables": {
    "test": {
      "name": "test",
      "schema": "my_schema",
      "columns": {
        "id": {
          "name": "id",
          "type": "serial",
          "primaryKey": true,
          "notNull": true
        },
        "name": {
          "name": "name",
          "type": "text",
          "primaryKey": false,
          "notNull": false
        }
      },
      "indexes": {},
      "foreignKeys": {},
      "compositePrimaryKeys": {},
      "uniqueConstraints": {}
    }
  },
  "enums": {},
  "schemas": {
    "my_schema": "my_schema"
  },
  "_meta": {
    "columns": {},
    "schemas": {},
    "tables": {}
  }
}